mouse_behavior_analysis_tools/__init__.py
mouse_behavior_analysis_tools/model/__init__.py
mouse_behavior_analysis_tools/model/behavior_model.py
mouse_behavior_analysis_tools/plot/__init__.py
mouse_behavior_analysis_tools/plot/make_figures.py
mouse_behavior_analysis_tools/utils/__init__.py
mouse_behavior_analysis_tools/utils/custom_functions.py
mouse_behavior_analysis_tools/utils/misc_utils.py
mouse_behavior_analysis_tools/utils/model_utils.py
mouse_behavior_analysis_tools/utils/plot_utils.py
mouse_behavior_analysis_tools-1.0.3.dist-info/LICENSE
mouse_behavior_analysis_tools-1.0.3.dist-info/METADATA
mouse_behavior_analysis_tools-1.0.3.dist-info/WHEEL
mouse_behavior_analysis_tools-1.0.3.dist-info/top_level.txt
mouse_behavior_analysis_tools-1.0.3.dist-info/RECORD
